hoardy_web/__init__.py
hoardy_web/__main__.py
hoardy_web/io.py
hoardy_web/linst.py
hoardy_web/mime.py
hoardy_web/mitmproxy.py
hoardy_web/output.py
hoardy_web/parser.py
hoardy_web/source.py
hoardy_web/type.py
hoardy_web/util.py
hoardy_web/web.py
hoardy_web/wire.py
hoardy_web/wrr.py
hoardy_web-0.18.1.dist-info/METADATA
hoardy_web-0.18.1.dist-info/WHEEL
hoardy_web-0.18.1.dist-info/entry_points.txt
hoardy_web-0.18.1.dist-info/top_level.txt
hoardy_web-0.18.1.dist-info/RECORD
