Metadata-Version: 2.1
Name: hoardy-web
Version: 0.18.1
Summary: Display, search, programmatically extract values from, organize, manipulate, import, and export Web Request+Response (`WRR`) files produced by the `Hoardy-Web` Web Extension browser add-on.
Author-email: Jan Malakhovski <oxij@oxij.org>
License: GPL-3.0-or-later
Project-URL: Homepage, https://oxij.org/software/hoardy-web/
Project-URL: GitHub, https://github.com/Own-Data-Privateer/hoardy-web
Project-URL: Support Development, https://oxij.org/#support
Keywords: HTTP,HTTPS,WWW,web,browser,site,website,download,archive,mirror,wayback,wayback machine
Classifier: Development Status :: 4 - Beta
Classifier: Programming Language :: Python :: 3
Classifier: License :: OSI Approved :: GNU General Public License v3 or later (GPLv3+)
Classifier: Intended Audience :: End Users/Desktop
Classifier: Topic :: Internet :: WWW/HTTP
Classifier: Topic :: Internet :: WWW/HTTP :: Indexing/Search
Classifier: Topic :: System :: Archiving
Classifier: Topic :: System :: Archiving :: Backup
Classifier: Topic :: System :: Archiving :: Mirroring
Classifier: Topic :: System :: Logging
Classifier: Topic :: Internet :: Log Analysis
Classifier: Operating System :: POSIX
Classifier: Environment :: Console
Requires-Python: >=3.10
Requires-Dist: kisstdlib==0.0.4
Requires-Dist: cbor2
Requires-Dist: idna
Requires-Dist: html5lib
Requires-Dist: tinycss2>=1.3.0
